{"name": "2024-02-11", "region": "ma-al", "origin": {"lng": -35.739118, "lat": -9.618276}, "vehicle_capacity": 50, "deliveries": [{"id": "31421", "point": {"lng": -35.7342209, "lat": -9.6208518}, "size": 1, "preparation": 20, "time": 43, "timestamp": 154}, {"id": "31423", "point": {"lng": -35.7342209, "lat": -9.6208518}, "size": 1, "preparation": 14, "time": 27, "timestamp": 154}, {"id": "31422", "point": {"lng": -35.7752337, "lat": -9.5885348}, "size": 1, "preparation": 30, "time": 57, "timestamp": 165}, {"id": "31420", "point": {"lng": -35.7509295, "lat": -9.5943923}, "size": 1, "preparation": 30, "time": 48, "timestamp": 165}, {"id": "31424", "point": {"lng": -35.7192917, "lat": -9.6189777}, "size": 1, "preparation": 9, "time": 28, "timestamp": 167}, {"id": "31425", "point": {"lng": -35.721956, "lat": -9.6284871}, "size": 1, "preparation": 18, "time": 33, "timestamp": 167}, {"id": "31426", "point": {"lng": -35.7058252, "lat": -9.6178778}, "size": 1, "preparation": 27, "time": 39, "timestamp": 216}, {"id": "31432", "point": {"lng": -35.7342209, "lat": -9.6208518}, "size": 1, "preparation": 28, "time": 40, "timestamp": 216}, {"id": "31429", "point": {"lng": -35.7574033, "lat": -9.605307}, "size": 1, "preparation": 8, "time": 23, "timestamp": 220}, {"id": "31431", "point": {"lng": -35.7342209, "lat": -9.6208518}, "size": 1, "preparation": 17, "time": 37, "timestamp": 220}, {"id": "31430", "point": {"lng": -35.721956, "lat": -9.6284871}, "size": 1, "preparation": 12, "time": 42, "timestamp": 230}, {"id": "31438", "point": {"lng": -35.721639, "lat": -9.6024662}, "size": 1, "preparation": 7, "time": 36, "timestamp": 230}, {"id": "31434", "point": {"lng": -35.7342209, "lat": -9.6208518}, "size": 1, "preparation": 27, "time": 50, "timestamp": 235}, {"id": "31435", "point": {"lng": -35.7380331, "lat": -9.5908531}, "size": 1, "preparation": 24, "time": 35, "timestamp": 235}, {"id": "31437", "point": {"lng": -35.7469512, "lat": -9.5934619}, "size": 1, "preparation": 8, "time": 23, "timestamp": 251}, {"id": "31441", "point": {"lng": -35.721639, "lat": -9.6024662}, "size": 1, "preparation": 7, "time": 23, "timestamp": 251}, {"id": "31439", "point": {"lng": -35.7342209, "lat": -9.6208518}, "size": 1, "preparation": 12, "time": 37, "timestamp": 254}, {"id": "31443", "point": {"lng": -35.7469512, "lat": -9.5934619}, "size": 1, "preparation": 16, "time": 32, "timestamp": 254}, {"id": "31440", "point": {"lng": -35.7380331, "lat": -9.5908531}, "size": 1, "preparation": 14, "time": 30, "timestamp": 263}, {"id": "31442", "point": {"lng": -35.7380331, "lat": -9.5908531}, "size": 1, "preparation": 12, "time": 34, "timestamp": 263}, {"id": "31450", "point": {"lng": -35.7469512, "lat": -9.5934619}, "size": 1, "preparation": 19, "time": 46, "timestamp": 287}, {"id": "31452", "point": {"lng": -35.7574033, "lat": -9.605307}, "size": 1, "preparation": 22, "time": 47, "timestamp": 288}, {"id": "31453", "point": {"lng": -35.7192917, "lat": -9.6189777}, "size": 1, "preparation": 27, "time": 56, "timestamp": 304}, {"id": "31462", "point": {"lng": -35.7192917, "lat": -9.6189777}, "size": 1, "preparation": 21, "time": 43, "timestamp": 304}, {"id": "31455", "point": {"lng": -35.7535285, "lat": -9.5813609}, "size": 1, "preparation": 20, "time": 50, "timestamp": 317}, {"id": "31463", "point": {"lng": -35.7342209, "lat": -9.6208518}, "size": 1, "preparation": 28, "time": 50, "timestamp": 317}, {"id": "31458", "point": {"lng": -35.7347635, "lat": -9.6499931}, "size": 1, "preparation": 5, "time": 20, "timestamp": 319}, {"id": "31459", "point": {"lng": -35.7347635, "lat": -9.6499931}, "size": 1, "preparation": 24, "time": 42, "timestamp": 319}, {"id": "31461", "point": {"lng": -35.7325694, "lat": -9.6372814}, "size": 1, "preparation": 10, "time": 26, "timestamp": 343}, {"id": "31464", "point": {"lng": -35.721639, "lat": -9.6024662}, "size": 1, "preparation": 10, "time": 26, "timestamp": 343}, {"id": "31467", "point": {"lng": -35.721639, "lat": -9.6024662}, "size": 1, "preparation": 23, "time": 43, "timestamp": 365}, {"id": "31468", "point": {"lng": -35.7192917, "lat": -9.6189777}, "size": 1, "preparation": 6, "time": 33, "timestamp": 365}, {"id": "31473", "point": {"lng": -35.721639, "lat": -9.6024662}, "size": 1, "preparation": 8, "time": 28, "timestamp": 413}, {"id": "31476", "point": {"lng": -35.7347635, "lat": -9.6499931}, "size": 1, "preparation": 12, "time": 28, "timestamp": 475}, {"id": "31477", "point": {"lng": -35.721639, "lat": -9.6024662}, "size": 1, "preparation": 23, "time": 51, "timestamp": 475}, {"id": "31481", "point": {"lng": -35.7380331, "lat": -9.5908531}, "size": 1, "preparation": 16, "time": 36, "timestamp": 532}, {"id": "31484", "point": {"lng": -35.7380331, "lat": -9.5908531}, "size": 1, "preparation": 28, "time": 53, "timestamp": 575}, {"id": "31486", "point": {"lng": -35.721639, "lat": -9.6024662}, "size": 1, "preparation": 16, "time": 36, "timestamp": 624}, {"id": "31487", "point": {"lng": -35.7058252, "lat": -9.6178778}, "size": 1, "preparation": 21, "time": 31, "timestamp": 624}, {"id": "31490", "point": {"lng": -35.7342209, "lat": -9.6208518}, "size": 1, "preparation": 12, "time": 41, "timestamp": 646}, {"id": "31491", "point": {"lng": -35.7058252, "lat": -9.6178778}, "size": 1, "preparation": 12, "time": 30, "timestamp": 646}, {"id": "31494", "point": {"lng": -35.7535285, "lat": -9.5813609}, "size": 1, "preparation": 21, "time": 44, "timestamp": 663}, {"id": "31497", "point": {"lng": -35.721956, "lat": -9.6284871}, "size": 1, "preparation": 20, "time": 30, "timestamp": 693}, {"id": "31500", "point": {"lng": -35.7342209, "lat": -9.6208518}, "size": 1, "preparation": 8, "time": 29, "timestamp": 693}, {"id": "31498", "point": {"lng": -35.7306858, "lat": -9.604452}, "size": 1, "preparation": 10, "time": 28, "timestamp": 698}, {"id": "31501", "point": {"lng": -35.7509295, "lat": -9.5943923}, "size": 1, "preparation": 17, "time": 27, "timestamp": 698}, {"id": "31503", "point": {"lng": -35.7306858, "lat": -9.604452}, "size": 1, "preparation": 24, "time": 46, "timestamp": 756}, {"id": "31507", "point": {"lng": -35.7342209, "lat": -9.6208518}, "size": 1, "preparation": 12, "time": 22, "timestamp": 756}, {"id": "31510", "point": {"lng": -35.7419526, "lat": -9.6321474}, "size": 1, "preparation": 10, "time": 23, "timestamp": 794}, {"id": "31511", "point": {"lng": -35.7342209, "lat": -9.6208518}, "size": 1, "preparation": 22, "time": 51, "timestamp": 794}, {"id": "31512", "point": {"lng": -35.7380331, "lat": -9.5908531}, "size": 1, "preparation": 13, "time": 31, "timestamp": 813}, {"id": "31514", "point": {"lng": -35.7192917, "lat": -9.6189777}, "size": 1, "preparation": 29, "time": 45, "timestamp": 814}, {"id": "31515", "point": {"lng": -35.721639, "lat": -9.6024662}, "size": 1, "preparation": 18, "time": 42, "timestamp": 814}]}